odoo/addons/mrp_product_produce_delay_in_hour/README.rst
odoo/addons/mrp_product_produce_delay_in_hour/__init__.py
odoo/addons/mrp_product_produce_delay_in_hour/__manifest__.py
odoo/addons/mrp_product_produce_delay_in_hour/data/decimal_precision.xml
odoo/addons/mrp_product_produce_delay_in_hour/i18n/fr.po
odoo/addons/mrp_product_produce_delay_in_hour/i18n/it.po
odoo/addons/mrp_product_produce_delay_in_hour/i18n/mrp_product_produce_delay_in_hour.pot
odoo/addons/mrp_product_produce_delay_in_hour/models/__init__.py
odoo/addons/mrp_product_produce_delay_in_hour/models/product_template.py
odoo/addons/mrp_product_produce_delay_in_hour/readme/CONTRIBUTORS.rst
odoo/addons/mrp_product_produce_delay_in_hour/readme/DESCRIPTION.rst
odoo/addons/mrp_product_produce_delay_in_hour/static/description/icon.png
odoo/addons/mrp_product_produce_delay_in_hour/static/description/index.html
odoo/addons/mrp_product_produce_delay_in_hour/static/description/mrp_product_produce_delay_hour.png
odoo/addons/mrp_product_produce_delay_in_hour/tests/__init__.py
odoo/addons/mrp_product_produce_delay_in_hour/tests/test_product_produce_delay.py
odoo/addons/mrp_product_produce_delay_in_hour/views/product_template.xml
odoo_addon_mrp_product_produce_delay_in_hour-16.0.1.0.0.6.dist-info/METADATA
odoo_addon_mrp_product_produce_delay_in_hour-16.0.1.0.0.6.dist-info/WHEEL
odoo_addon_mrp_product_produce_delay_in_hour-16.0.1.0.0.6.dist-info/top_level.txt
odoo_addon_mrp_product_produce_delay_in_hour-16.0.1.0.0.6.dist-info/RECORD
